nbsurvey/__init__.py
nbsurvey/lib.py
nbsurvey-0.0.1.dist-info/LICENSE.txt
nbsurvey-0.0.1.dist-info/METADATA
nbsurvey-0.0.1.dist-info/WHEEL
nbsurvey-0.0.1.dist-info/top_level.txt
nbsurvey-0.0.1.dist-info/RECORD
