Metadata-Version: 2.1
Name: nbsurvey
Version: 0.0.1
Summary: work in progress
Author-email: Alexander Schau <alexander@schau.email>
Project-URL: Homepage, https://instant-feedback.click
Classifier: Programming Language :: Python :: 3
Classifier: Operating System :: OS Independent
Requires-Python: >=3.6
License-File: LICENSE.txt
